<?xml version="1.0" encoding="utf-8" ?>
<USER_OVERRIDES>
    <!-- Placeholder -->
    <!--
    <LIVERY_OVERRIDE LIVERY="51-60" NAME="Team Name: Car Number" BASELIVERY="Default|Matte|Chrome">
        <PREVIEWIMAGE PATH="teamid\preview.dds" />
        <TEXTURE NAME="BODY" PATH="teamid\body.dds" />
        <TEXTURE NAME="SPEC" PATH="teamid\spec.dds" />
        <TEXTURE NAME="FRESNEL" PATH="teamid\fresnel.dds" />
    </LIVERY_OVERRIDE>
    -->

    <!-- KCSR -->
    <LIVERY_OVERRIDE LIVERY="51" NAME="Kerb Clippers Bruce" BASELIVERY="Chrome">
        <PREVIEWIMAGE PATH="kcsr\KC_M8GTE_Thumb_Bruce.dds" />
        <TEXTURE NAME="BODY" PATH="kcsr\KC_M8GTE_Bruce.dds" />
        <TEXTURE NAME="SPEC" PATH="kcsr\KC_M8GTE_Bruce_spec.dds" />
        <TEXTURE NAME="FRESNEL" PATH="kcsr\KC_M8GTE_Bruce_fresnel.dds" />
    </LIVERY_OVERRIDE>
    
    <!-- NRT -->
    
    <!-- RPM -->
    <LIVERY_OVERRIDE LIVERY="53" NAME="RPM League" BASELIVERY="Default">
        <PREVIEWIMAGE PATH="rpm\preview86.dds" />
        <TEXTURE NAME="BODY" PATH="rpm\body86.dds" />
    </LIVERY_OVERRIDE>
    
    <!-- MGT -->
    
    <!-- AMSU -->
    <LIVERY_OVERRIDE LIVERY="55" NAME="AMSU" BASELIVERY="Default">
        <PREVIEWIMAGE PATH="amsu\amsu--preview.DDS" />
        <TEXTURE NAME="BODY" PATH="amsu\amsu-bmw-body.DDS" />
    </LIVERY_OVERRIDE>
    
    <!-- PRC -->
    <LIVERY_OVERRIDE LIVERY="56" NAME="PRC" BASELIVERY="Chrome">
        <PREVIEWIMAGE PATH="prc\PRC_M8GTE_thumb.dds" />
        <TEXTURE NAME="BODY" PATH="prc\PRC_M8GTE.dds" />
        <TEXTURE NAME="SPEC" PATH="prc\PRC_M8GTE_spec.dds" />
    </LIVERY_OVERRIDE>
    
    <!-- AMS2CC -->

</USER_OVERRIDES>
